mcs_matplotlib/__init__.py
mcs_matplotlib/eqToPNG.py
mcs_matplotlib-1.0.1.dist-info/METADATA
mcs_matplotlib-1.0.1.dist-info/WHEEL
mcs_matplotlib-1.0.1.dist-info/entry_points.txt
mcs_matplotlib-1.0.1.dist-info/top_level.txt
mcs_matplotlib-1.0.1.dist-info/RECORD
