Metadata-Version: 2.1
Name: mcs-matplotlib
Version: 1.0.1
Summary: More utilities for matplotlib
Home-page: https://github.com/moderncoursesquare/pythonlib
Author: moderncoursesquare
Author-email: moderncoursesquare@gmail.com
License: MIT
Platform: UNKNOWN
Classifier: License :: OSI Approved :: MIT License
Classifier: Programming Language :: Python :: 3
Classifier: Programming Language :: Python :: 3.7
Requires-Dist: feedparser
Requires-Dist: html2text
